cdata/__init__.py
cdata/core.py
cdata/entity.py
cdata/misc.py
cdata/region.py
cdata/table.py
cdata/web.py
cdata-0.1.2.dist-info/DESCRIPTION.rst
cdata-0.1.2.dist-info/METADATA
cdata-0.1.2.dist-info/RECORD
cdata-0.1.2.dist-info/WHEEL
cdata-0.1.2.dist-info/metadata.json
cdata-0.1.2.dist-info/top_level.txt
