Metadata-Version: 2.0
Name: cdata
Version: 0.1.2
Summary: see data, handy snippets for conversion, and ETL.
Home-page: http://github.com/cnschema/cdata
Author: Li Ding
Author-email: lidingpku@gmail.com
License: Apache 2.0
Platform: UNKNOWN
Classifier: Development Status :: 3 - Alpha
Classifier: License :: OSI Approved :: Apache Software License
Classifier: Programming Language :: Python :: 2.7
Classifier: Topic :: Text Processing
Requires-Dist: jieba
Requires-Dist: xlrd
Requires-Dist: xlwt
